<annotation>
	<folder>imagenes_resize</folder>
	<filename>s47.jpg</filename>
	<path>D:\U\Semestre IV mecánica\Róbotica\proyecto\semaforos_resized\content\imagenes_resize\s47.jpg</path>
	<source>
		<database>Unknown</database>
	</source>
	<size>
		<width>224</width>
		<height>224</height>
		<depth>3</depth>
	</size>
	<segmented>0</segmented>
	<object>
		<name>semaforo</name>
		<pose>Unspecified</pose>
		<truncated>0</truncated>
		<difficult>0</difficult>
		<bndbox>
			<xmin>101</xmin>
			<ymin>7</ymin>
			<xmax>124</xmax>
			<ymax>69</ymax>
		</bndbox>
	</object>
</annotation>
